{
    "Symbol": "AOS",
    "Historical_Data": [
        {
            "Date": "2024-07-10",
            "Open": 80.51374109170997,
            "High": 82.44773405586602,
            "Low": 80.41456332348275,
            "Close": 82.30888366699219,
            "Volume": 1014100,
            "Dividends": 0.0,
            "Stock Splits": 0.0
        },
        {
            "Date": "2024-07-11",
            "Open": 83.49903970755248,
            "High": 85.67106083197004,
            "Low": 83.08248097354617,
            "Close": 85.37352752685547,
            "Volume": 1004700,
            "Dividends": 0.0,
            "Stock Splits": 0.0
        },
        {
            "Date": "2024-07-12",
            "Open": 86.22648151536958,
            "High": 87.91252650406832,
            "Low": 85.93886065178597,
            "Close": 87.10917663574219,
            "Volume": 999000,
            "Dividends": 0.0,
            "Stock Splits": 0.0
        },
        {
            "Date": "2024-07-15",
            "Open": 87.49596554439606,
            "High": 88.45800580975876,
            "Low": 86.98022903026525,
            "Close": 87.07941436767578,
            "Volume": 1154700,
            "Dividends": 0.0,
            "Stock Splits": 0.0
        },
        {
            "Date": "2024-07-16",
            "Open": 88.04144373147167,
            "High": 91.3837881992889,
            "Low": 87.77366300423117,
            "Close": 91.22510528564453,
            "Volume": 1338300,
            "Dividends": 0.0,
            "Stock Splits": 0.0
        },
        {
            "Date": "2024-07-17",
            "Open": 90.71930157725794,
            "High": 91.37388098397713,
            "Low": 89.40021514892578,
            "Close": 89.40021514892578,
            "Volume": 850900,
            "Dividends": 0.0,
            "Stock Splits": 0.0
        },
        {
            "Date": "2024-07-18",
            "Open": 89.06300299011592,
            "High": 91.69124804919844,
            "Low": 88.11087517361234,
            "Close": 88.28939819335938,
            "Volume": 1025900,
            "Dividends": 0.0,
            "Stock Splits": 0.0
        },
        {
            "Date": "2024-07-19",
            "Open": 88.62661174335686,
            "High": 88.94398516006981,
            "Low": 86.85130159253846,
            "Close": 87.26785278320312,
            "Volume": 1038600,
            "Dividends": 0.0,
            "Stock Splits": 0.0
        },
        {
            "Date": "2024-07-22",
            "Open": 87.4265439852282,
            "High": 88.34891166735304,
            "Low": 85.95868719176853,
            "Close": 88.08112335205078,
            "Volume": 1138800,
            "Dividends": 0.0,
            "Stock Splits": 0.0
        },
        {
            "Date": "2024-07-23",
            "Open": 80.25587405968952,
            "High": 84.37181582124379,
            "Low": 79.17482350607193,
            "Close": 79.8095703125,
            "Volume": 2721300,
            "Dividends": 0.0,
            "Stock Splits": 0.0
        },
        {
            "Date": "2024-07-24",
            "Open": 80.21620879420979,
            "High": 81.82291605162783,
            "Low": 79.9881006595836,
            "Close": 80.09719848632812,
            "Volume": 2167100,
            "Dividends": 0.0,
            "Stock Splits": 0.0
        },
        {
            "Date": "2024-07-25",
            "Open": 80.50382601588903,
            "High": 82.64610226241807,
            "Low": 80.44432086463405,
            "Close": 81.50553894042969,
            "Volume": 1505600,
            "Dividends": 0.0,
            "Stock Splits": 0.0
        },
        {
            "Date": "2024-07-26",
            "Open": 82.86429548749739,
            "High": 84.21313436628876,
            "Low": 82.61634727546631,
            "Close": 83.8064956665039,
            "Volume": 1149800,
            "Dividends": 0.0,
            "Stock Splits": 0.0
        },
        {
            "Date": "2024-07-29",
            "Open": 83.8064956665039,
            "High": 84.59001292453559,
            "Low": 83.13207622710821,
            "Close": 83.8064956665039,
            "Volume": 1059000,
            "Dividends": 0.0,
            "Stock Splits": 0.0
        },
        {
            "Date": "2024-07-30",
            "Open": 84.5205948659925,
            "High": 85.274359612924,
            "Low": 84.29247916227577,
            "Close": 84.74870300292969,
            "Volume": 881100,
            "Dividends": 0.0,
            "Stock Splits": 0.0
        },
        {
            "Date": "2024-07-31",
            "Open": 85.23651505493585,
            "High": 85.46548064316386,
            "Low": 84.3803663441206,
            "Close": 84.65911102294922,
            "Volume": 1746400,
            "Dividends": 0.32,
            "Stock Splits": 0.0
        },
        {
            "Date": "2024-08-01",
            "Open": 84.63919114415928,
            "High": 85.48539006099996,
            "Low": 80.99558827387995,
            "Close": 82.17030334472656,
            "Volume": 874700,
            "Dividends": 0.0,
            "Stock Splits": 0.0
        },
        {
            "Date": "2024-08-02",
            "Open": 81.33406032829063,
            "High": 82.09065839324477,
            "Low": 79.91046503532725,
            "Close": 82.03092956542969,
            "Volume": 1106000,
            "Dividends": 0.0,
            "Stock Splits": 0.0
        },
        {
            "Date": "2024-08-05",
            "Open": 80.36841659792637,
            "High": 82.19021432188475,
            "Low": 79.31315913475561,
            "Close": 81.28429412841797,
            "Volume": 1243300,
            "Dividends": 0.0,
            "Stock Splits": 0.0
        },
        {
            "Date": "2024-08-06",
            "Open": 81.43362282406241,
            "High": 83.05631935935605,
            "Low": 80.92590497501808,
            "Close": 81.29425048828125,
            "Volume": 860000,
            "Dividends": 0.0,
            "Stock Splits": 0.0
        },
        {
            "Date": "2024-08-07",
            "Open": 81.62276642741858,
            "High": 83.24547055343184,
            "Low": 79.60185996897712,
            "Close": 79.91046905517578,
            "Volume": 1291700,
            "Dividends": 0.0,
            "Stock Splits": 0.0
        },
        {
            "Date": "2024-08-08",
            "Open": 80.43810276998445,
            "High": 81.12500712027021,
            "Low": 79.43262439667339,
            "Close": 80.12948608398438,
            "Volume": 1075100,
            "Dividends": 0.0,
            "Stock Splits": 0.0
        },
        {
            "Date": "2024-08-09",
            "Open": 80.16930664743222,
            "High": 80.90599007669158,
            "Low": 79.25342913049111,
            "Close": 79.91046905517578,
            "Volume": 628000,
            "Dividends": 0.0,
            "Stock Splits": 0.0
        },
        {
            "Date": "2024-08-12",
            "Open": 79.85074105804816,
            "High": 80.04984982156373,
            "Low": 78.40723859986822,
            "Close": 78.5167465209961,
            "Volume": 698800,
            "Dividends": 0.0,
            "Stock Splits": 0.0
        },
        {
            "Date": "2024-08-13",
            "Open": 79.15387895695717,
            "High": 79.43262362918831,
            "Low": 78.27781559254768,
            "Close": 79.21360778808594,
            "Volume": 679900,
            "Dividends": 0.0,
            "Stock Splits": 0.0
        },
        {
            "Date": "2024-08-14",
            "Open": 79.59189955933913,
            "High": 79.9901094716165,
            "Low": 78.81539440777053,
            "Close": 79.40275573730469,
            "Volume": 652200,
            "Dividends": 0.0,
            "Stock Splits": 0.0
        },
        {
            "Date": "2024-08-15",
            "Open": 80.49783241069902,
            "High": 80.88608501113464,
            "Low": 79.50231136440813,
            "Close": 79.89056396484375,
            "Volume": 735100,
            "Dividends": 0.0,
            "Stock Splits": 0.0
        },
        {
            "Date": "2024-08-16",
            "Open": 79.80096888622437,
            "High": 80.15934946706497,
            "Low": 79.07423519720093,
            "Close": 79.29325103759766,
            "Volume": 834200,
            "Dividends": 0.0,
            "Stock Splits": 0.0
        },
        {
            "Date": "2024-08-19",
            "Open": 79.55208424217976,
            "High": 80.34849645988284,
            "Low": 79.23351024083185,
            "Close": 80.33853912353516,
            "Volume": 584900,
            "Dividends": 0.0,
            "Stock Splits": 0.0
        },
        {
            "Date": "2024-08-20",
            "Open": 80.2688583737307,
            "High": 80.74671181276184,
            "Low": 80.01997811480717,
            "Close": 80.43810272216797,
            "Volume": 605300,
            "Dividends": 0.0,
            "Stock Splits": 0.0
        },
        {
            "Date": "2024-08-21",
            "Open": 80.82635553596947,
            "High": 81.57299631474918,
            "Low": 80.65711118707678,
            "Close": 81.51325988769531,
            "Volume": 573100,
            "Dividends": 0.0,
            "Stock Splits": 0.0
        },
        {
            "Date": "2024-08-22",
            "Open": 81.45352874878164,
            "High": 81.73227341639527,
            "Low": 80.5177365687451,
            "Close": 80.76661682128906,
            "Volume": 627700,
            "Dividends": 0.0,
            "Stock Splits": 0.0
        },
        {
            "Date": "2024-08-23",
            "Open": 81.45352701740016,
            "High": 82.71783533155138,
            "Low": 80.81639419204834,
            "Close": 82.17030334472656,
            "Volume": 562300,
            "Dividends": 0.0,
            "Stock Splits": 0.0
        },
        {
            "Date": "2024-08-26",
            "Open": 82.5884228478935,
            "High": 82.84726043956816,
            "Low": 81.75218883740666,
            "Close": 81.9911117553711,
            "Volume": 562100,
            "Dividends": 0.0,
            "Stock Splits": 0.0
        },
        {
            "Date": "2024-08-27",
            "Open": 81.48339207213364,
            "High": 82.02097432185276,
            "Low": 80.62724340723528,
            "Close": 81.393798828125,
            "Volume": 702400,
            "Dividends": 0.0,
            "Stock Splits": 0.0
        },
        {
            "Date": "2024-08-28",
            "Open": 81.3539767899852,
            "High": 82.27981161758898,
            "Low": 81.22455419991023,
            "Close": 81.47343444824219,
            "Volume": 577000,
            "Dividends": 0.0,
            "Stock Splits": 0.0
        },
        {
            "Date": "2024-08-29",
            "Open": 82.0309362704355,
            "High": 82.56851855037864,
            "Low": 80.76662028004435,
            "Close": 81.7322769165039,
            "Volume": 603700,
            "Dividends": 0.0,
            "Stock Splits": 0.0
        },
        {
            "Date": "2024-08-30",
            "Open": 82.1105726084516,
            "High": 83.48438880709892,
            "Low": 82.06079352206825,
            "Close": 83.34501647949219,
            "Volume": 1007100,
            "Dividends": 0.0,
            "Stock Splits": 0.0
        },
        {
            "Date": "2024-09-03",
            "Open": 83.15587128994255,
            "High": 83.29524362798168,
            "Low": 80.28877342785123,
            "Close": 80.89604187011719,
            "Volume": 740800,
            "Dividends": 0.0,
            "Stock Splits": 0.0
        },
        {
            "Date": "2024-09-04",
            "Open": 80.7267957315978,
            "High": 80.89604007708503,
            "Low": 79.40275854957292,
            "Close": 79.9901123046875,
            "Volume": 625100,
            "Dividends": 0.0,
            "Stock Splits": 0.0
        },
        {
            "Date": "2024-09-05",
            "Open": 79.51226802849203,
            "High": 79.59190393915186,
            "Low": 76.59539108374108,
            "Close": 77.51126861572266,
            "Volume": 1561800,
            "Dividends": 0.0,
            "Stock Splits": 0.0
        },
        {
            "Date": "2024-09-06",
            "Open": 77.6904571989958,
            "High": 78.27781092399219,
            "Low": 76.43609865354402,
            "Close": 76.56552124023438,
            "Volume": 864900,
            "Dividends": 0.0,
            "Stock Splits": 0.0
        },
        {
            "Date": "2024-09-09",
            "Open": 76.98364073650752,
            "High": 77.64068064685233,
            "Low": 76.45601582185516,
            "Close": 77.54113006591797,
            "Volume": 830900,
            "Dividends": 0.0,
            "Stock Splits": 0.0
        },
        {
            "Date": "2024-09-10",
            "Open": 77.79000870222164,
            "High": 78.45700593539071,
            "Low": 77.36193437738342,
            "Close": 78.32759094238281,
            "Volume": 556700,
            "Dividends": 0.0,
            "Stock Splits": 0.0
        },
        {
            "Date": "2024-09-11",
            "Open": 78.12848858617599,
            "High": 78.21808182721736,
            "Low": 76.28676872684437,
            "Close": 78.10857391357422,
            "Volume": 593100,
            "Dividends": 0.0,
            "Stock Splits": 0.0
        },
        {
            "Date": "2024-09-12",
            "Open": 78.0488515127556,
            "High": 79.06427963761247,
            "Low": 77.53117631559498,
            "Close": 79.04437255859375,
            "Volume": 982200,
            "Dividends": 0.0,
            "Stock Splits": 0.0
        },
        {
            "Date": "2024-09-13",
            "Open": 79.39280056875576,
            "High": 80.22903457167281,
            "Low": 79.0642768125144,
            "Close": 79.61181640625,
            "Volume": 986200,
            "Dividends": 0.0,
            "Stock Splits": 0.0
        },
        {
            "Date": "2024-09-16",
            "Open": 80.4580049446918,
            "High": 81.56303383523256,
            "Low": 80.08965944943743,
            "Close": 81.33406066894531,
            "Volume": 821000,
            "Dividends": 0.0,
            "Stock Splits": 0.0
        },
        {
            "Date": "2024-09-17",
            "Open": 81.72231362164717,
            "High": 82.87712160442454,
            "Low": 81.56303421432546,
            "Close": 82.10061645507812,
            "Volume": 583600,
            "Dividends": 0.0,
            "Stock Splits": 0.0
        },
        {
            "Date": "2024-09-18",
            "Open": 82.52869512995812,
            "High": 83.91246875779471,
            "Low": 81.93138402938206,
            "Close": 82.51873779296875,
            "Volume": 904200,
            "Dividends": 0.0,
            "Stock Splits": 0.0
        },
        {
            "Date": "2024-09-19",
            "Open": 84.12152645998722,
            "High": 84.12152645998722,
            "Low": 82.9866331011626,
            "Close": 83.91246795654297,
            "Volume": 679500,
            "Dividends": 0.0,
            "Stock Splits": 0.0
        },
        {
            "Date": "2024-09-20",
            "Open": 83.64367382564072,
            "High": 83.81291817356916,
            "Low": 82.24995045603748,
            "Close": 82.51873779296875,
            "Volume": 2338900,
            "Dividends": 0.0,
            "Stock Splits": 0.0
        },
        {
            "Date": "2024-09-23",
            "Open": 82.92690434754131,
            "High": 83.82286719307395,
            "Low": 82.70788850699861,
            "Close": 83.6038589477539,
            "Volume": 668400,
            "Dividends": 0.0,
            "Stock Splits": 0.0
        },
        {
            "Date": "2024-09-24",
            "Open": 83.66358955126334,
            "High": 85.38583670615985,
            "Low": 83.46448078508672,
            "Close": 85.35597229003906,
            "Volume": 940700,
            "Dividends": 0.0,
            "Stock Splits": 0.0
        },
        {
            "Date": "2024-09-25",
            "Open": 85.5849432233023,
            "High": 85.73427289520492,
            "Low": 84.77857362833986,
            "Close": 85.45552062988281,
            "Volume": 805800,
            "Dividends": 0.0,
            "Stock Splits": 0.0
        },
        {
            "Date": "2024-09-26",
            "Open": 86.54064345640363,
            "High": 89.50729946820536,
            "Low": 86.3614493671643,
            "Close": 88.90998077392578,
            "Volume": 1799400,
            "Dividends": 0.0,
            "Stock Splits": 0.0
        },
        {
            "Date": "2024-09-27",
            "Open": 89.56702409971446,
            "High": 91.64765930949913,
            "Low": 89.41769443314669,
            "Close": 90.18424224853516,
            "Volume": 1631300,
            "Dividends": 0.0,
            "Stock Splits": 0.0
        },
        {
            "Date": "2024-09-30",
            "Open": 90.19419825575125,
            "High": 90.43312116160504,
            "Low": 89.07921963161874,
            "Close": 89.42765045166016,
            "Volume": 1065800,
            "Dividends": 0.0,
            "Stock Splits": 0.0
        },
        {
            "Date": "2024-10-01",
            "Open": 89.5570693256661,
            "High": 89.74622074841221,
            "Low": 87.83482222827743,
            "Close": 88.54164123535156,
            "Volume": 847600,
            "Dividends": 0.0,
            "Stock Splits": 0.0
        },
        {
            "Date": "2024-10-02",
            "Open": 88.0239642490042,
            "High": 88.14342950226892,
            "Low": 86.7397412584925,
            "Close": 87.63571166992188,
            "Volume": 981900,
            "Dividends": 0.0,
            "Stock Splits": 0.0
        },
        {
            "Date": "2024-10-03",
            "Open": 87.24745698368191,
            "High": 87.62575221705018,
            "Low": 86.1722925159335,
            "Close": 87.1180419921875,
            "Volume": 886000,
            "Dividends": 0.0,
            "Stock Splits": 0.0
        },
        {
            "Date": "2024-10-04",
            "Open": 87.68549187919481,
            "High": 87.74522070897999,
            "Low": 86.35148978395367,
            "Close": 87.00853729248047,
            "Volume": 653500,
            "Dividends": 0.0,
            "Stock Splits": 0.0
        },
        {
            "Date": "2024-10-07",
            "Open": 86.49086439680875,
            "High": 88.01401795348282,
            "Low": 85.90351063451216,
            "Close": 87.75518035888672,
            "Volume": 629900,
            "Dividends": 0.0,
            "Stock Splits": 0.0
        },
        {
            "Date": "2024-10-08",
            "Open": 87.35697029275167,
            "High": 87.4764355505091,
            "Low": 85.54512232382201,
            "Close": 86.06278991699219,
            "Volume": 1536800,
            "Dividends": 0.0,
            "Stock Splits": 0.0
        },
        {
            "Date": "2024-10-09",
            "Open": 86.59042316307887,
            "High": 87.48638602043782,
            "Low": 86.46100056729203,
            "Close": 87.28728485107422,
            "Volume": 635500,
            "Dividends": 0.0,
            "Stock Splits": 0.0
        },
        {
            "Date": "2024-10-10",
            "Open": 86.6103253672232,
            "High": 86.99857794228608,
            "Low": 85.77409138869466,
            "Close": 85.87364196777344,
            "Volume": 808400,
            "Dividends": 0.0,
            "Stock Splits": 0.0
        },
        {
            "Date": "2024-10-11",
            "Open": 79.98015707818642,
            "High": 82.82734787338622,
            "Low": 79.14392304642175,
            "Close": 80.5077896118164,
            "Volume": 2379100,
            "Dividends": 0.0,
            "Stock Splits": 0.0
        },
        {
            "Date": "2024-10-14",
            "Open": 80.66706427704734,
            "High": 82.33953983726789,
            "Low": 80.28876903666287,
            "Close": 82.24994659423828,
            "Volume": 1345400,
            "Dividends": 0.0,
            "Stock Splits": 0.0
        },
        {
            "Date": "2024-10-15",
            "Open": 82.13048588359324,
            "High": 82.63820374117239,
            "Low": 80.5376537370166,
            "Close": 80.5874252319336,
            "Volume": 1379200,
            "Dividends": 0.0,
            "Stock Splits": 0.0
        },
        {
            "Date": "2024-10-16",
            "Open": 80.99558721369941,
            "High": 81.55307652977947,
            "Low": 79.84077923585095,
            "Close": 79.87065124511719,
            "Volume": 1158100,
            "Dividends": 0.0,
            "Stock Splits": 0.0
        },
        {
            "Date": "2024-10-17",
            "Open": 79.51226407325575,
            "High": 79.87065223667712,
            "Low": 77.8696529234449,
            "Close": 78.39727783203125,
            "Volume": 1772800,
            "Dividends": 0.0,
            "Stock Splits": 0.0
        },
        {
            "Date": "2024-10-18",
            "Open": 78.64615807911706,
            "High": 78.81539482428205,
            "Low": 77.92938175227434,
            "Close": 78.39727783203125,
            "Volume": 1032200,
            "Dividends": 0.0,
            "Stock Splits": 0.0
        },
        {
            "Date": "2024-10-21",
            "Open": 78.4769208607071,
            "High": 79.24346867521099,
            "Low": 77.7601445381868,
            "Close": 78.2479476928711,
            "Volume": 1196600,
            "Dividends": 0.0,
            "Stock Splits": 0.0
        },
        {
            "Date": "2024-10-22",
            "Open": 79.3032054219773,
            "High": 79.90051649477016,
            "Low": 77.65063693885394,
            "Close": 77.85969543457031,
            "Volume": 1549900,
            "Dividends": 0.0,
            "Stock Splits": 0.0
        },
        {
            "Date": "2024-10-23",
            "Open": 77.64067779843747,
            "High": 79.8805999657855,
            "Low": 76.88408733491544,
            "Close": 76.95377349853516,
            "Volume": 1396300,
            "Dividends": 0.0,
            "Stock Splits": 0.0
        },
        {
            "Date": "2024-10-24",
            "Open": 76.8542189747375,
            "High": 77.6506388212496,
            "Low": 76.1872217205366,
            "Close": 76.99359130859375,
            "Volume": 851400,
            "Dividends": 0.0,
            "Stock Splits": 0.0
        },
        {
            "Date": "2024-10-25",
            "Open": 77.02346393945051,
            "High": 77.76014736651476,
            "Low": 76.31664492770712,
            "Close": 76.52570343017578,
            "Volume": 822000,
            "Dividends": 0.0,
            "Stock Splits": 0.0
        },
        {
            "Date": "2024-10-28",
            "Open": 76.9836446189612,
            "High": 77.89952216210304,
            "Low": 76.595392017081,
            "Close": 76.65512084960938,
            "Volume": 710300,
            "Dividends": 0.0,
            "Stock Splits": 0.0
        },
        {
            "Date": "2024-10-29",
            "Open": 75.71932412430904,
            "High": 76.69493803712044,
            "Low": 75.17179213654201,
            "Close": 76.00802612304688,
            "Volume": 877300,
            "Dividends": 0.0,
            "Stock Splits": 0.0
        },
        {
            "Date": "2024-10-30",
            "Open": 75.72927909885709,
            "High": 76.5655206545017,
            "Low": 75.37089094575542,
            "Close": 75.56999969482422,
            "Volume": 917400,
            "Dividends": 0.0,
            "Stock Splits": 0.0
        },
        {
            "Date": "2024-10-31",
            "Open": 75.41000366210938,
            "High": 75.83000183105469,
            "Low": 74.80999755859375,
            "Close": 75.0999984741211,
            "Volume": 1977500,
            "Dividends": 0.34,
            "Stock Splits": 0.0
        },
        {
            "Date": "2024-11-01",
            "Open": 75.41000366210938,
            "High": 76.30999755859375,
            "Low": 75.02999877929688,
            "Close": 75.4000015258789,
            "Volume": 811300,
            "Dividends": 0.0,
            "Stock Splits": 0.0
        },
        {
            "Date": "2024-11-04",
            "Open": 75.4000015258789,
            "High": 76.27999877929688,
            "Low": 74.80000305175781,
            "Close": 75.13999938964844,
            "Volume": 716400,
            "Dividends": 0.0,
            "Stock Splits": 0.0
        },
        {
            "Date": "2024-11-05",
            "Open": 75.0,
            "High": 75.98999786376953,
            "Low": 74.80000305175781,
            "Close": 75.91999816894531,
            "Volume": 709000,
            "Dividends": 0.0,
            "Stock Splits": 0.0
        },
        {
            "Date": "2024-11-06",
            "Open": 77.0,
            "High": 77.91999816894531,
            "Low": 75.47000122070312,
            "Close": 76.20999908447266,
            "Volume": 1422200,
            "Dividends": 0.0,
            "Stock Splits": 0.0
        },
        {
            "Date": "2024-11-07",
            "Open": 76.26000213623047,
            "High": 76.66000366210938,
            "Low": 75.66000366210938,
            "Close": 76.02999877929688,
            "Volume": 1299000,
            "Dividends": 0.0,
            "Stock Splits": 0.0
        },
        {
            "Date": "2024-11-08",
            "Open": 76.01000213623047,
            "High": 76.27999877929688,
            "Low": 74.80999755859375,
            "Close": 74.86000061035156,
            "Volume": 1289400,
            "Dividends": 0.0,
            "Stock Splits": 0.0
        },
        {
            "Date": "2024-11-11",
            "Open": 75.08000183105469,
            "High": 75.70999908447266,
            "Low": 74.69000244140625,
            "Close": 75.0999984741211,
            "Volume": 1215100,
            "Dividends": 0.0,
            "Stock Splits": 0.0
        },
        {
            "Date": "2024-11-12",
            "Open": 74.70999908447266,
            "High": 75.08000183105469,
            "Low": 73.05000305175781,
            "Close": 73.13999938964844,
            "Volume": 1323800,
            "Dividends": 0.0,
            "Stock Splits": 0.0
        },
        {
            "Date": "2024-11-13",
            "Open": 73.37999725341797,
            "High": 73.5,
            "Low": 72.62000274658203,
            "Close": 73.11000061035156,
            "Volume": 1066400,
            "Dividends": 0.0,
            "Stock Splits": 0.0
        },
        {
            "Date": "2024-11-14",
            "Open": 73.0,
            "High": 73.80000305175781,
            "Low": 72.91000366210938,
            "Close": 73.0,
            "Volume": 1002400,
            "Dividends": 0.0,
            "Stock Splits": 0.0
        },
        {
            "Date": "2024-11-15",
            "Open": 72.77999877929688,
            "High": 73.27999877929688,
            "Low": 72.1500015258789,
            "Close": 72.2300033569336,
            "Volume": 1214400,
            "Dividends": 0.0,
            "Stock Splits": 0.0
        },
        {
            "Date": "2024-11-18",
            "Open": 72.0,
            "High": 72.62999725341797,
            "Low": 71.63999938964844,
            "Close": 72.1500015258789,
            "Volume": 801700,
            "Dividends": 0.0,
            "Stock Splits": 0.0
        },
        {
            "Date": "2024-11-19",
            "Open": 71.5199966430664,
            "High": 72.0,
            "Low": 71.04000091552734,
            "Close": 71.41000366210938,
            "Volume": 914200,
            "Dividends": 0.0,
            "Stock Splits": 0.0
        },
        {
            "Date": "2024-11-20",
            "Open": 71.5,
            "High": 71.93000030517578,
            "Low": 70.7300033569336,
            "Close": 71.75,
            "Volume": 849600,
            "Dividends": 0.0,
            "Stock Splits": 0.0
        },
        {
            "Date": "2024-11-21",
            "Open": 71.75,
            "High": 73.56999969482422,
            "Low": 71.69000244140625,
            "Close": 72.97000122070312,
            "Volume": 975900,
            "Dividends": 0.0,
            "Stock Splits": 0.0
        },
        {
            "Date": "2024-11-22",
            "Open": 73.0999984741211,
            "High": 73.80000305175781,
            "Low": 73.0,
            "Close": 73.44000244140625,
            "Volume": 716600,
            "Dividends": 0.0,
            "Stock Splits": 0.0
        },
        {
            "Date": "2024-11-25",
            "Open": 74.11000061035156,
            "High": 75.91000366210938,
            "Low": 74.01000213623047,
            "Close": 75.43000030517578,
            "Volume": 1303100,
            "Dividends": 0.0,
            "Stock Splits": 0.0
        },
        {
            "Date": "2024-11-26",
            "Open": 74.52999877929688,
            "High": 74.58999633789062,
            "Low": 73.75,
            "Close": 73.9000015258789,
            "Volume": 850800,
            "Dividends": 0.0,
            "Stock Splits": 0.0
        },
        {
            "Date": "2024-11-27",
            "Open": 74.2300033569336,
            "High": 74.93000030517578,
            "Low": 74.01000213623047,
            "Close": 74.0999984741211,
            "Volume": 609100,
            "Dividends": 0.0,
            "Stock Splits": 0.0
        },
        {
            "Date": "2024-11-29",
            "Open": 74.19999694824219,
            "High": 74.66999816894531,
            "Low": 74.05000305175781,
            "Close": 74.48999786376953,
            "Volume": 381300,
            "Dividends": 0.0,
            "Stock Splits": 0.0
        },
        {
            "Date": "2024-12-02",
            "Open": 74.62999725341797,
            "High": 74.86000061035156,
            "Low": 73.75,
            "Close": 74.6500015258789,
            "Volume": 841200,
            "Dividends": 0.0,
            "Stock Splits": 0.0
        },
        {
            "Date": "2024-12-03",
            "Open": 74.6500015258789,
            "High": 74.6500015258789,
            "Low": 73.23999786376953,
            "Close": 74.0199966430664,
            "Volume": 1134100,
            "Dividends": 0.0,
            "Stock Splits": 0.0
        },
        {
            "Date": "2024-12-04",
            "Open": 73.79000091552734,
            "High": 74.13999938964844,
            "Low": 73.2300033569336,
            "Close": 73.5999984741211,
            "Volume": 865200,
            "Dividends": 0.0,
            "Stock Splits": 0.0
        },
        {
            "Date": "2024-12-05",
            "Open": 73.52999877929688,
            "High": 73.58000183105469,
            "Low": 71.9800033569336,
            "Close": 72.31999969482422,
            "Volume": 939100,
            "Dividends": 0.0,
            "Stock Splits": 0.0
        },
        {
            "Date": "2024-12-06",
            "Open": 73.23999786376953,
            "High": 73.23999786376953,
            "Low": 72.30999755859375,
            "Close": 72.61000061035156,
            "Volume": 1066700,
            "Dividends": 0.0,
            "Stock Splits": 0.0
        },
        {
            "Date": "2024-12-09",
            "Open": 72.77999877929688,
            "High": 74.41999816894531,
            "Low": 72.77999877929688,
            "Close": 73.88999938964844,
            "Volume": 1313900,
            "Dividends": 0.0,
            "Stock Splits": 0.0
        },
        {
            "Date": "2024-12-10",
            "Open": 73.5999984741211,
            "High": 73.8499984741211,
            "Low": 72.08000183105469,
            "Close": 72.9800033569336,
            "Volume": 954600,
            "Dividends": 0.0,
            "Stock Splits": 0.0
        },
        {
            "Date": "2024-12-11",
            "Open": 73.4000015258789,
            "High": 73.69000244140625,
            "Low": 72.45999908447266,
            "Close": 72.87999725341797,
            "Volume": 1084800,
            "Dividends": 0.0,
            "Stock Splits": 0.0
        },
        {
            "Date": "2024-12-12",
            "Open": 72.66999816894531,
            "High": 73.1500015258789,
            "Low": 72.19000244140625,
            "Close": 72.62999725341797,
            "Volume": 864800,
            "Dividends": 0.0,
            "Stock Splits": 0.0
        },
        {
            "Date": "2024-12-13",
            "Open": 72.27999877929688,
            "High": 72.81999969482422,
            "Low": 72.08000183105469,
            "Close": 72.48999786376953,
            "Volume": 981500,
            "Dividends": 0.0,
            "Stock Splits": 0.0
        },
        {
            "Date": "2024-12-16",
            "Open": 72.12999725341797,
            "High": 73.4000015258789,
            "Low": 71.80000305175781,
            "Close": 71.88999938964844,
            "Volume": 767900,
            "Dividends": 0.0,
            "Stock Splits": 0.0
        },
        {
            "Date": "2024-12-17",
            "Open": 71.66000366210938,
            "High": 72.20999908447266,
            "Low": 70.76000213623047,
            "Close": 70.80999755859375,
            "Volume": 1148900,
            "Dividends": 0.0,
            "Stock Splits": 0.0
        },
        {
            "Date": "2024-12-18",
            "Open": 71.08000183105469,
            "High": 71.69999694824219,
            "Low": 68.88999938964844,
            "Close": 68.91000366210938,
            "Volume": 812600,
            "Dividends": 0.0,
            "Stock Splits": 0.0
        },
        {
            "Date": "2024-12-19",
            "Open": 68.94000244140625,
            "High": 69.91999816894531,
            "Low": 68.37999725341797,
            "Close": 68.44000244140625,
            "Volume": 1300000,
            "Dividends": 0.0,
            "Stock Splits": 0.0
        },
        {
            "Date": "2024-12-20",
            "Open": 68.23999786376953,
            "High": 69.41000366210938,
            "Low": 68.06999969482422,
            "Close": 68.72000122070312,
            "Volume": 2859700,
            "Dividends": 0.0,
            "Stock Splits": 0.0
        },
        {
            "Date": "2024-12-23",
            "Open": 68.22000122070312,
            "High": 68.68000030517578,
            "Low": 68.0999984741211,
            "Close": 68.55999755859375,
            "Volume": 574400,
            "Dividends": 0.0,
            "Stock Splits": 0.0
        },
        {
            "Date": "2024-12-24",
            "Open": 68.4800033569336,
            "High": 68.88999938964844,
            "Low": 68.1500015258789,
            "Close": 68.88999938964844,
            "Volume": 381800,
            "Dividends": 0.0,
            "Stock Splits": 0.0
        },
        {
            "Date": "2024-12-26",
            "Open": 68.63999938964844,
            "High": 69.23999786376953,
            "Low": 68.47000122070312,
            "Close": 68.88999938964844,
            "Volume": 670600,
            "Dividends": 0.0,
            "Stock Splits": 0.0
        },
        {
            "Date": "2024-12-27",
            "Open": 68.5999984741211,
            "High": 69.06999969482422,
            "Low": 68.2300033569336,
            "Close": 68.43000030517578,
            "Volume": 517900,
            "Dividends": 0.0,
            "Stock Splits": 0.0
        },
        {
            "Date": "2024-12-30",
            "Open": 68.1500015258789,
            "High": 68.2300033569336,
            "Low": 67.38999938964844,
            "Close": 68.0199966430664,
            "Volume": 838900,
            "Dividends": 0.0,
            "Stock Splits": 0.0
        },
        {
            "Date": "2024-12-31",
            "Open": 68.3499984741211,
            "High": 68.68000030517578,
            "Low": 67.68000030517578,
            "Close": 68.20999908447266,
            "Volume": 792000,
            "Dividends": 0.0,
            "Stock Splits": 0.0
        },
        {
            "Date": "2025-01-02",
            "Open": 68.51000213623047,
            "High": 69.31999969482422,
            "Low": 67.29000091552734,
            "Close": 67.33000183105469,
            "Volume": 815300,
            "Dividends": 0.0,
            "Stock Splits": 0.0
        },
        {
            "Date": "2025-01-03",
            "Open": 67.45999908447266,
            "High": 68.77999877929688,
            "Low": 67.16999816894531,
            "Close": 68.5999984741211,
            "Volume": 932800,
            "Dividends": 0.0,
            "Stock Splits": 0.0
        },
        {
            "Date": "2025-01-06",
            "Open": 68.87000274658203,
            "High": 69.54000091552734,
            "Low": 68.38999938964844,
            "Close": 68.9000015258789,
            "Volume": 1531100,
            "Dividends": 0.0,
            "Stock Splits": 0.0
        },
        {
            "Date": "2025-01-07",
            "Open": 68.72000122070312,
            "High": 69.33000183105469,
            "Low": 67.95999908447266,
            "Close": 68.30000305175781,
            "Volume": 943900,
            "Dividends": 0.0,
            "Stock Splits": 0.0
        },
        {
            "Date": "2025-01-08",
            "Open": 67.87000274658203,
            "High": 68.76000213623047,
            "Low": 67.29000091552734,
            "Close": 68.68000030517578,
            "Volume": 977700,
            "Dividends": 0.0,
            "Stock Splits": 0.0
        },
        {
            "Date": "2025-01-10",
            "Open": 67.87999725341797,
            "High": 68.86499786376953,
            "Low": 67.87999725341797,
            "Close": 68.69999694824219,
            "Volume": 234868,
            "Dividends": 0.0,
            "Stock Splits": 0.0
        }
    ]
}