{
    "Symbol": "CNC",
    "Historical_Data": [
        {
            "Date": "2024-07-10",
            "Open": 65.72000122070312,
            "High": 66.69999694824219,
            "Low": 65.61000061035156,
            "Close": 66.66000366210938,
            "Volume": 2678200,
            "Dividends": 0.0,
            "Stock Splits": 0.0
        },
        {
            "Date": "2024-07-11",
            "Open": 66.01000213623047,
            "High": 67.7699966430664,
            "Low": 65.69999694824219,
            "Close": 67.25,
            "Volume": 3937900,
            "Dividends": 0.0,
            "Stock Splits": 0.0
        },
        {
            "Date": "2024-07-12",
            "Open": 67.72000122070312,
            "High": 68.33000183105469,
            "Low": 67.16999816894531,
            "Close": 67.86000061035156,
            "Volume": 4033700,
            "Dividends": 0.0,
            "Stock Splits": 0.0
        },
        {
            "Date": "2024-07-15",
            "Open": 67.56999969482422,
            "High": 67.97000122070312,
            "Low": 65.81999969482422,
            "Close": 66.0,
            "Volume": 3878700,
            "Dividends": 0.0,
            "Stock Splits": 0.0
        },
        {
            "Date": "2024-07-16",
            "Open": 67.33000183105469,
            "High": 69.29000091552734,
            "Low": 66.66000366210938,
            "Close": 69.11000061035156,
            "Volume": 5283100,
            "Dividends": 0.0,
            "Stock Splits": 0.0
        },
        {
            "Date": "2024-07-17",
            "Open": 67.08999633789062,
            "High": 68.1500015258789,
            "Low": 66.18000030517578,
            "Close": 67.80000305175781,
            "Volume": 4311300,
            "Dividends": 0.0,
            "Stock Splits": 0.0
        },
        {
            "Date": "2024-07-18",
            "Open": 67.29000091552734,
            "High": 67.63999938964844,
            "Low": 65.54000091552734,
            "Close": 65.69000244140625,
            "Volume": 4162600,
            "Dividends": 0.0,
            "Stock Splits": 0.0
        },
        {
            "Date": "2024-07-19",
            "Open": 66.68000030517578,
            "High": 67.0,
            "Low": 65.77999877929688,
            "Close": 66.23999786376953,
            "Volume": 3541700,
            "Dividends": 0.0,
            "Stock Splits": 0.0
        },
        {
            "Date": "2024-07-22",
            "Open": 65.91999816894531,
            "High": 66.63999938964844,
            "Low": 65.6500015258789,
            "Close": 66.13999938964844,
            "Volume": 2765300,
            "Dividends": 0.0,
            "Stock Splits": 0.0
        },
        {
            "Date": "2024-07-23",
            "Open": 65.5,
            "High": 66.12000274658203,
            "Low": 63.45000076293945,
            "Close": 64.88999938964844,
            "Volume": 5344000,
            "Dividends": 0.0,
            "Stock Splits": 0.0
        },
        {
            "Date": "2024-07-24",
            "Open": 65.16000366210938,
            "High": 66.38999938964844,
            "Low": 64.68000030517578,
            "Close": 66.12000274658203,
            "Volume": 4216500,
            "Dividends": 0.0,
            "Stock Splits": 0.0
        },
        {
            "Date": "2024-07-25",
            "Open": 66.66999816894531,
            "High": 68.27999877929688,
            "Low": 66.66999816894531,
            "Close": 67.4000015258789,
            "Volume": 5449800,
            "Dividends": 0.0,
            "Stock Splits": 0.0
        },
        {
            "Date": "2024-07-26",
            "Open": 69.44999694824219,
            "High": 74.72000122070312,
            "Low": 69.30000305175781,
            "Close": 73.0999984741211,
            "Volume": 9686500,
            "Dividends": 0.0,
            "Stock Splits": 0.0
        },
        {
            "Date": "2024-07-29",
            "Open": 73.38999938964844,
            "High": 73.7699966430664,
            "Low": 71.4800033569336,
            "Close": 73.4800033569336,
            "Volume": 3907800,
            "Dividends": 0.0,
            "Stock Splits": 0.0
        },
        {
            "Date": "2024-07-30",
            "Open": 73.62999725341797,
            "High": 77.19999694824219,
            "Low": 73.38999938964844,
            "Close": 77.0999984741211,
            "Volume": 6236300,
            "Dividends": 0.0,
            "Stock Splits": 0.0
        },
        {
            "Date": "2024-07-31",
            "Open": 76.77999877929688,
            "High": 78.30999755859375,
            "Low": 76.75,
            "Close": 76.91999816894531,
            "Volume": 6826600,
            "Dividends": 0.0,
            "Stock Splits": 0.0
        },
        {
            "Date": "2024-08-01",
            "Open": 77.47000122070312,
            "High": 77.9800033569336,
            "Low": 75.08000183105469,
            "Close": 77.91000366210938,
            "Volume": 4525300,
            "Dividends": 0.0,
            "Stock Splits": 0.0
        },
        {
            "Date": "2024-08-02",
            "Open": 78.0,
            "High": 78.88999938964844,
            "Low": 77.05999755859375,
            "Close": 78.08999633789062,
            "Volume": 4553200,
            "Dividends": 0.0,
            "Stock Splits": 0.0
        },
        {
            "Date": "2024-08-05",
            "Open": 77.19999694824219,
            "High": 78.44000244140625,
            "Low": 76.41999816894531,
            "Close": 77.43000030517578,
            "Volume": 3483200,
            "Dividends": 0.0,
            "Stock Splits": 0.0
        },
        {
            "Date": "2024-08-06",
            "Open": 77.27999877929688,
            "High": 77.73999786376953,
            "Low": 75.43000030517578,
            "Close": 75.44000244140625,
            "Volume": 4200000,
            "Dividends": 0.0,
            "Stock Splits": 0.0
        },
        {
            "Date": "2024-08-07",
            "Open": 75.31999969482422,
            "High": 76.22000122070312,
            "Low": 74.72000122070312,
            "Close": 74.77999877929688,
            "Volume": 3658300,
            "Dividends": 0.0,
            "Stock Splits": 0.0
        },
        {
            "Date": "2024-08-08",
            "Open": 74.86000061035156,
            "High": 76.3499984741211,
            "Low": 74.77999877929688,
            "Close": 75.5199966430664,
            "Volume": 2812200,
            "Dividends": 0.0,
            "Stock Splits": 0.0
        },
        {
            "Date": "2024-08-09",
            "Open": 75.36000061035156,
            "High": 76.4800033569336,
            "Low": 75.01000213623047,
            "Close": 76.0,
            "Volume": 2566700,
            "Dividends": 0.0,
            "Stock Splits": 0.0
        },
        {
            "Date": "2024-08-12",
            "Open": 76.2699966430664,
            "High": 76.93000030517578,
            "Low": 75.44000244140625,
            "Close": 75.66999816894531,
            "Volume": 3355000,
            "Dividends": 0.0,
            "Stock Splits": 0.0
        },
        {
            "Date": "2024-08-13",
            "Open": 75.9800033569336,
            "High": 76.5,
            "Low": 75.69000244140625,
            "Close": 76.3499984741211,
            "Volume": 2305900,
            "Dividends": 0.0,
            "Stock Splits": 0.0
        },
        {
            "Date": "2024-08-14",
            "Open": 76.38999938964844,
            "High": 77.33000183105469,
            "Low": 76.20999908447266,
            "Close": 77.02999877929688,
            "Volume": 2532200,
            "Dividends": 0.0,
            "Stock Splits": 0.0
        },
        {
            "Date": "2024-08-15",
            "Open": 77.06999969482422,
            "High": 78.77999877929688,
            "Low": 77.01000213623047,
            "Close": 78.51000213623047,
            "Volume": 3197500,
            "Dividends": 0.0,
            "Stock Splits": 0.0
        },
        {
            "Date": "2024-08-16",
            "Open": 78.58999633789062,
            "High": 78.66999816894531,
            "Low": 77.75,
            "Close": 78.11000061035156,
            "Volume": 2348500,
            "Dividends": 0.0,
            "Stock Splits": 0.0
        },
        {
            "Date": "2024-08-19",
            "Open": 78.30000305175781,
            "High": 78.81999969482422,
            "Low": 78.05999755859375,
            "Close": 78.30000305175781,
            "Volume": 1695500,
            "Dividends": 0.0,
            "Stock Splits": 0.0
        },
        {
            "Date": "2024-08-20",
            "Open": 78.26000213623047,
            "High": 79.01000213623047,
            "Low": 77.9800033569336,
            "Close": 78.16000366210938,
            "Volume": 2519600,
            "Dividends": 0.0,
            "Stock Splits": 0.0
        },
        {
            "Date": "2024-08-21",
            "Open": 78.45999908447266,
            "High": 78.76000213623047,
            "Low": 78.12000274658203,
            "Close": 78.4000015258789,
            "Volume": 2833800,
            "Dividends": 0.0,
            "Stock Splits": 0.0
        },
        {
            "Date": "2024-08-22",
            "Open": 78.44000244140625,
            "High": 79.19000244140625,
            "Low": 77.81999969482422,
            "Close": 78.2300033569336,
            "Volume": 2538900,
            "Dividends": 0.0,
            "Stock Splits": 0.0
        },
        {
            "Date": "2024-08-23",
            "Open": 78.2300033569336,
            "High": 79.06999969482422,
            "Low": 78.20999908447266,
            "Close": 78.55000305175781,
            "Volume": 2123200,
            "Dividends": 0.0,
            "Stock Splits": 0.0
        },
        {
            "Date": "2024-08-26",
            "Open": 78.86000061035156,
            "High": 79.08000183105469,
            "Low": 77.55999755859375,
            "Close": 77.66999816894531,
            "Volume": 2025800,
            "Dividends": 0.0,
            "Stock Splits": 0.0
        },
        {
            "Date": "2024-08-27",
            "Open": 77.94000244140625,
            "High": 78.2300033569336,
            "Low": 77.30999755859375,
            "Close": 78.0,
            "Volume": 2553600,
            "Dividends": 0.0,
            "Stock Splits": 0.0
        },
        {
            "Date": "2024-08-28",
            "Open": 78.0999984741211,
            "High": 78.44999694824219,
            "Low": 77.4000015258789,
            "Close": 78.16999816894531,
            "Volume": 3122100,
            "Dividends": 0.0,
            "Stock Splits": 0.0
        },
        {
            "Date": "2024-08-29",
            "Open": 78.62000274658203,
            "High": 78.62000274658203,
            "Low": 77.3499984741211,
            "Close": 78.29000091552734,
            "Volume": 2425600,
            "Dividends": 0.0,
            "Stock Splits": 0.0
        },
        {
            "Date": "2024-08-30",
            "Open": 78.44000244140625,
            "High": 79.0,
            "Low": 77.91000366210938,
            "Close": 78.83000183105469,
            "Volume": 3063600,
            "Dividends": 0.0,
            "Stock Splits": 0.0
        },
        {
            "Date": "2024-09-03",
            "Open": 78.83000183105469,
            "High": 80.58999633789062,
            "Low": 78.7300033569336,
            "Close": 80.2300033569336,
            "Volume": 2979200,
            "Dividends": 0.0,
            "Stock Splits": 0.0
        },
        {
            "Date": "2024-09-04",
            "Open": 74.11000061035156,
            "High": 75.48999786376953,
            "Low": 72.80000305175781,
            "Close": 73.26000213623047,
            "Volume": 6084600,
            "Dividends": 0.0,
            "Stock Splits": 0.0
        },
        {
            "Date": "2024-09-05",
            "Open": 73.26000213623047,
            "High": 73.58999633789062,
            "Low": 70.83999633789062,
            "Close": 72.66000366210938,
            "Volume": 6556500,
            "Dividends": 0.0,
            "Stock Splits": 0.0
        },
        {
            "Date": "2024-09-06",
            "Open": 72.94000244140625,
            "High": 73.33000183105469,
            "Low": 70.73999786376953,
            "Close": 70.83000183105469,
            "Volume": 6046700,
            "Dividends": 0.0,
            "Stock Splits": 0.0
        },
        {
            "Date": "2024-09-09",
            "Open": 71.27999877929688,
            "High": 71.45999908447266,
            "Low": 70.55000305175781,
            "Close": 70.83999633789062,
            "Volume": 5929200,
            "Dividends": 0.0,
            "Stock Splits": 0.0
        },
        {
            "Date": "2024-09-10",
            "Open": 70.80999755859375,
            "High": 71.66999816894531,
            "Low": 70.61000061035156,
            "Close": 71.0,
            "Volume": 4412400,
            "Dividends": 0.0,
            "Stock Splits": 0.0
        },
        {
            "Date": "2024-09-11",
            "Open": 72.2699966430664,
            "High": 74.22000122070312,
            "Low": 72.08000183105469,
            "Close": 73.47000122070312,
            "Volume": 5834900,
            "Dividends": 0.0,
            "Stock Splits": 0.0
        },
        {
            "Date": "2024-09-12",
            "Open": 73.66999816894531,
            "High": 75.13999938964844,
            "Low": 72.63999938964844,
            "Close": 74.81999969482422,
            "Volume": 4073200,
            "Dividends": 0.0,
            "Stock Splits": 0.0
        },
        {
            "Date": "2024-09-13",
            "Open": 74.9000015258789,
            "High": 75.43000030517578,
            "Low": 74.61000061035156,
            "Close": 75.3499984741211,
            "Volume": 2618500,
            "Dividends": 0.0,
            "Stock Splits": 0.0
        },
        {
            "Date": "2024-09-16",
            "Open": 75.97000122070312,
            "High": 77.18000030517578,
            "Low": 75.77999877929688,
            "Close": 76.56999969482422,
            "Volume": 4339600,
            "Dividends": 0.0,
            "Stock Splits": 0.0
        },
        {
            "Date": "2024-09-17",
            "Open": 77.0199966430664,
            "High": 77.29000091552734,
            "Low": 75.23999786376953,
            "Close": 75.38999938964844,
            "Volume": 4176600,
            "Dividends": 0.0,
            "Stock Splits": 0.0
        },
        {
            "Date": "2024-09-18",
            "Open": 75.41999816894531,
            "High": 77.0,
            "Low": 75.3499984741211,
            "Close": 76.31999969482422,
            "Volume": 3825800,
            "Dividends": 0.0,
            "Stock Splits": 0.0
        },
        {
            "Date": "2024-09-19",
            "Open": 76.83000183105469,
            "High": 77.16999816894531,
            "Low": 75.38999938964844,
            "Close": 75.62999725341797,
            "Volume": 3986400,
            "Dividends": 0.0,
            "Stock Splits": 0.0
        },
        {
            "Date": "2024-09-20",
            "Open": 75.33999633789062,
            "High": 75.8499984741211,
            "Low": 75.1500015258789,
            "Close": 75.61000061035156,
            "Volume": 6827900,
            "Dividends": 0.0,
            "Stock Splits": 0.0
        },
        {
            "Date": "2024-09-23",
            "Open": 75.9000015258789,
            "High": 76.08000183105469,
            "Low": 75.05000305175781,
            "Close": 75.3499984741211,
            "Volume": 3773900,
            "Dividends": 0.0,
            "Stock Splits": 0.0
        },
        {
            "Date": "2024-09-24",
            "Open": 75.05000305175781,
            "High": 75.37999725341797,
            "Low": 74.27999877929688,
            "Close": 74.4000015258789,
            "Volume": 4130600,
            "Dividends": 0.0,
            "Stock Splits": 0.0
        },
        {
            "Date": "2024-09-25",
            "Open": 74.83000183105469,
            "High": 74.97000122070312,
            "Low": 73.91999816894531,
            "Close": 74.12000274658203,
            "Volume": 3375200,
            "Dividends": 0.0,
            "Stock Splits": 0.0
        },
        {
            "Date": "2024-09-26",
            "Open": 74.12000274658203,
            "High": 74.70999908447266,
            "Low": 73.19000244140625,
            "Close": 73.69999694824219,
            "Volume": 3830400,
            "Dividends": 0.0,
            "Stock Splits": 0.0
        },
        {
            "Date": "2024-09-27",
            "Open": 74.30999755859375,
            "High": 75.0999984741211,
            "Low": 74.19000244140625,
            "Close": 74.58000183105469,
            "Volume": 3800300,
            "Dividends": 0.0,
            "Stock Splits": 0.0
        },
        {
            "Date": "2024-09-30",
            "Open": 74.81999969482422,
            "High": 75.3499984741211,
            "Low": 74.08000183105469,
            "Close": 75.27999877929688,
            "Volume": 2738500,
            "Dividends": 0.0,
            "Stock Splits": 0.0
        },
        {
            "Date": "2024-10-01",
            "Open": 75.27999877929688,
            "High": 75.27999877929688,
            "Low": 73.87999725341797,
            "Close": 73.94000244140625,
            "Volume": 4600500,
            "Dividends": 0.0,
            "Stock Splits": 0.0
        },
        {
            "Date": "2024-10-02",
            "Open": 73.5999984741211,
            "High": 73.81999969482422,
            "Low": 72.44000244140625,
            "Close": 72.62000274658203,
            "Volume": 4023100,
            "Dividends": 0.0,
            "Stock Splits": 0.0
        },
        {
            "Date": "2024-10-03",
            "Open": 72.62000274658203,
            "High": 72.62999725341797,
            "Low": 71.08000183105469,
            "Close": 72.04000091552734,
            "Volume": 3864400,
            "Dividends": 0.0,
            "Stock Splits": 0.0
        },
        {
            "Date": "2024-10-04",
            "Open": 72.2300033569336,
            "High": 72.72000122070312,
            "Low": 71.68000030517578,
            "Close": 72.08000183105469,
            "Volume": 4578400,
            "Dividends": 0.0,
            "Stock Splits": 0.0
        },
        {
            "Date": "2024-10-07",
            "Open": 71.91000366210938,
            "High": 72.16000366210938,
            "Low": 71.16999816894531,
            "Close": 71.48999786376953,
            "Volume": 5182500,
            "Dividends": 0.0,
            "Stock Splits": 0.0
        },
        {
            "Date": "2024-10-08",
            "Open": 72.05999755859375,
            "High": 72.19000244140625,
            "Low": 71.1500015258789,
            "Close": 71.33999633789062,
            "Volume": 2794400,
            "Dividends": 0.0,
            "Stock Splits": 0.0
        },
        {
            "Date": "2024-10-09",
            "Open": 71.62000274658203,
            "High": 72.69000244140625,
            "Low": 71.61000061035156,
            "Close": 72.3499984741211,
            "Volume": 2059600,
            "Dividends": 0.0,
            "Stock Splits": 0.0
        },
        {
            "Date": "2024-10-10",
            "Open": 72.6500015258789,
            "High": 72.6500015258789,
            "Low": 71.11000061035156,
            "Close": 71.62000274658203,
            "Volume": 3987900,
            "Dividends": 0.0,
            "Stock Splits": 0.0
        },
        {
            "Date": "2024-10-11",
            "Open": 71.9000015258789,
            "High": 73.5,
            "Low": 71.75,
            "Close": 72.44000244140625,
            "Volume": 3541700,
            "Dividends": 0.0,
            "Stock Splits": 0.0
        },
        {
            "Date": "2024-10-14",
            "Open": 72.47000122070312,
            "High": 73.13999938964844,
            "Low": 71.80999755859375,
            "Close": 72.9000015258789,
            "Volume": 3666600,
            "Dividends": 0.0,
            "Stock Splits": 0.0
        },
        {
            "Date": "2024-10-15",
            "Open": 69.55000305175781,
            "High": 71.04000091552734,
            "Low": 68.41000366210938,
            "Close": 68.4800033569336,
            "Volume": 6868100,
            "Dividends": 0.0,
            "Stock Splits": 0.0
        },
        {
            "Date": "2024-10-16",
            "Open": 68.73999786376953,
            "High": 69.36000061035156,
            "Low": 68.20999908447266,
            "Close": 69.30000305175781,
            "Volume": 4706300,
            "Dividends": 0.0,
            "Stock Splits": 0.0
        },
        {
            "Date": "2024-10-17",
            "Open": 63.0,
            "High": 63.459999084472656,
            "Low": 62.099998474121094,
            "Close": 63.0,
            "Volume": 14593600,
            "Dividends": 0.0,
            "Stock Splits": 0.0
        },
        {
            "Date": "2024-10-18",
            "Open": 63.13999938964844,
            "High": 63.13999938964844,
            "Low": 61.619998931884766,
            "Close": 62.02000045776367,
            "Volume": 5846000,
            "Dividends": 0.0,
            "Stock Splits": 0.0
        },
        {
            "Date": "2024-10-21",
            "Open": 61.970001220703125,
            "High": 62.529998779296875,
            "Low": 60.970001220703125,
            "Close": 61.0,
            "Volume": 14953400,
            "Dividends": 0.0,
            "Stock Splits": 0.0
        },
        {
            "Date": "2024-10-22",
            "Open": 60.90999984741211,
            "High": 61.36000061035156,
            "Low": 60.650001525878906,
            "Close": 61.060001373291016,
            "Volume": 5269200,
            "Dividends": 0.0,
            "Stock Splits": 0.0
        },
        {
            "Date": "2024-10-23",
            "Open": 61.09000015258789,
            "High": 61.4900016784668,
            "Low": 59.77000045776367,
            "Close": 59.81999969482422,
            "Volume": 6306800,
            "Dividends": 0.0,
            "Stock Splits": 0.0
        },
        {
            "Date": "2024-10-24",
            "Open": 61.599998474121094,
            "High": 62.88999938964844,
            "Low": 61.29999923706055,
            "Close": 61.619998931884766,
            "Volume": 10131000,
            "Dividends": 0.0,
            "Stock Splits": 0.0
        },
        {
            "Date": "2024-10-25",
            "Open": 70.0,
            "High": 70.11000061035156,
            "Low": 64.16000366210938,
            "Close": 64.22000122070312,
            "Volume": 12143200,
            "Dividends": 0.0,
            "Stock Splits": 0.0
        },
        {
            "Date": "2024-10-28",
            "Open": 63.650001525878906,
            "High": 63.720001220703125,
            "Low": 61.29999923706055,
            "Close": 61.650001525878906,
            "Volume": 8623400,
            "Dividends": 0.0,
            "Stock Splits": 0.0
        },
        {
            "Date": "2024-10-29",
            "Open": 61.599998474121094,
            "High": 61.709999084472656,
            "Low": 60.38999938964844,
            "Close": 60.619998931884766,
            "Volume": 6383000,
            "Dividends": 0.0,
            "Stock Splits": 0.0
        },
        {
            "Date": "2024-10-30",
            "Open": 60.4900016784668,
            "High": 62.34000015258789,
            "Low": 60.4900016784668,
            "Close": 61.779998779296875,
            "Volume": 6635500,
            "Dividends": 0.0,
            "Stock Splits": 0.0
        },
        {
            "Date": "2024-10-31",
            "Open": 61.779998779296875,
            "High": 62.7599983215332,
            "Low": 61.279998779296875,
            "Close": 62.2599983215332,
            "Volume": 6450000,
            "Dividends": 0.0,
            "Stock Splits": 0.0
        },
        {
            "Date": "2024-11-01",
            "Open": 62.31999969482422,
            "High": 63.91999816894531,
            "Low": 62.25,
            "Close": 63.52000045776367,
            "Volume": 6313000,
            "Dividends": 0.0,
            "Stock Splits": 0.0
        },
        {
            "Date": "2024-11-04",
            "Open": 64.0,
            "High": 65.4000015258789,
            "Low": 63.72999954223633,
            "Close": 63.81999969482422,
            "Volume": 5930100,
            "Dividends": 0.0,
            "Stock Splits": 0.0
        },
        {
            "Date": "2024-11-05",
            "Open": 63.47999954223633,
            "High": 64.88999938964844,
            "Low": 62.93000030517578,
            "Close": 64.80000305175781,
            "Volume": 6211000,
            "Dividends": 0.0,
            "Stock Splits": 0.0
        },
        {
            "Date": "2024-11-06",
            "Open": 60.0,
            "High": 63.09000015258789,
            "Low": 59.939998626708984,
            "Close": 62.560001373291016,
            "Volume": 9724700,
            "Dividends": 0.0,
            "Stock Splits": 0.0
        },
        {
            "Date": "2024-11-07",
            "Open": 62.70000076293945,
            "High": 63.540000915527344,
            "Low": 62.099998474121094,
            "Close": 62.52000045776367,
            "Volume": 6586200,
            "Dividends": 0.0,
            "Stock Splits": 0.0
        },
        {
            "Date": "2024-11-08",
            "Open": 62.84000015258789,
            "High": 62.84000015258789,
            "Low": 60.13999938964844,
            "Close": 60.150001525878906,
            "Volume": 6328500,
            "Dividends": 0.0,
            "Stock Splits": 0.0
        },
        {
            "Date": "2024-11-11",
            "Open": 61.41999816894531,
            "High": 62.2400016784668,
            "Low": 60.72999954223633,
            "Close": 60.75,
            "Volume": 5376600,
            "Dividends": 0.0,
            "Stock Splits": 0.0
        },
        {
            "Date": "2024-11-12",
            "Open": 60.849998474121094,
            "High": 61.25,
            "Low": 58.560001373291016,
            "Close": 58.599998474121094,
            "Volume": 6229900,
            "Dividends": 0.0,
            "Stock Splits": 0.0
        },
        {
            "Date": "2024-11-13",
            "Open": 58.75,
            "High": 59.189998626708984,
            "Low": 57.560001373291016,
            "Close": 58.040000915527344,
            "Volume": 7003900,
            "Dividends": 0.0,
            "Stock Splits": 0.0
        },
        {
            "Date": "2024-11-14",
            "Open": 58.27000045776367,
            "High": 59.86000061035156,
            "Low": 58.22999954223633,
            "Close": 58.68000030517578,
            "Volume": 6854900,
            "Dividends": 0.0,
            "Stock Splits": 0.0
        },
        {
            "Date": "2024-11-15",
            "Open": 58.70000076293945,
            "High": 59.20000076293945,
            "Low": 57.25,
            "Close": 57.459999084472656,
            "Volume": 8033600,
            "Dividends": 0.0,
            "Stock Splits": 0.0
        },
        {
            "Date": "2024-11-18",
            "Open": 57.369998931884766,
            "High": 58.93000030517578,
            "Low": 57.20000076293945,
            "Close": 58.83000183105469,
            "Volume": 5238300,
            "Dividends": 0.0,
            "Stock Splits": 0.0
        },
        {
            "Date": "2024-11-19",
            "Open": 58.25,
            "High": 58.790000915527344,
            "Low": 57.7599983215332,
            "Close": 57.810001373291016,
            "Volume": 7426900,
            "Dividends": 0.0,
            "Stock Splits": 0.0
        },
        {
            "Date": "2024-11-20",
            "Open": 58.20000076293945,
            "High": 59.439998626708984,
            "Low": 58.0,
            "Close": 59.099998474121094,
            "Volume": 4562900,
            "Dividends": 0.0,
            "Stock Splits": 0.0
        },
        {
            "Date": "2024-11-21",
            "Open": 59.400001525878906,
            "High": 60.43000030517578,
            "Low": 58.5,
            "Close": 60.349998474121094,
            "Volume": 6849100,
            "Dividends": 0.0,
            "Stock Splits": 0.0
        },
        {
            "Date": "2024-11-22",
            "Open": 60.189998626708984,
            "High": 60.720001220703125,
            "Low": 59.84000015258789,
            "Close": 60.369998931884766,
            "Volume": 4143000,
            "Dividends": 0.0,
            "Stock Splits": 0.0
        },
        {
            "Date": "2024-11-25",
            "Open": 60.849998474121094,
            "High": 61.90999984741211,
            "Low": 60.72999954223633,
            "Close": 61.43000030517578,
            "Volume": 6401900,
            "Dividends": 0.0,
            "Stock Splits": 0.0
        },
        {
            "Date": "2024-11-26",
            "Open": 61.400001525878906,
            "High": 61.810001373291016,
            "Low": 59.88999938964844,
            "Close": 60.0,
            "Volume": 5544000,
            "Dividends": 0.0,
            "Stock Splits": 0.0
        },
        {
            "Date": "2024-11-27",
            "Open": 60.11000061035156,
            "High": 60.650001525878906,
            "Low": 59.66999816894531,
            "Close": 59.93000030517578,
            "Volume": 3468400,
            "Dividends": 0.0,
            "Stock Splits": 0.0
        },
        {
            "Date": "2024-11-29",
            "Open": 59.68000030517578,
            "High": 60.40999984741211,
            "Low": 59.439998626708984,
            "Close": 60.0,
            "Volume": 2380200,
            "Dividends": 0.0,
            "Stock Splits": 0.0
        },
        {
            "Date": "2024-12-02",
            "Open": 60.310001373291016,
            "High": 60.34000015258789,
            "Low": 59.02000045776367,
            "Close": 60.060001373291016,
            "Volume": 3895500,
            "Dividends": 0.0,
            "Stock Splits": 0.0
        },
        {
            "Date": "2024-12-03",
            "Open": 60.25,
            "High": 60.400001525878906,
            "Low": 58.880001068115234,
            "Close": 59.40999984741211,
            "Volume": 5300800,
            "Dividends": 0.0,
            "Stock Splits": 0.0
        },
        {
            "Date": "2024-12-04",
            "Open": 59.41999816894531,
            "High": 59.9900016784668,
            "Low": 58.7400016784668,
            "Close": 59.77000045776367,
            "Volume": 4948100,
            "Dividends": 0.0,
            "Stock Splits": 0.0
        },
        {
            "Date": "2024-12-05",
            "Open": 59.68000030517578,
            "High": 59.75,
            "Low": 57.86000061035156,
            "Close": 57.95000076293945,
            "Volume": 4060400,
            "Dividends": 0.0,
            "Stock Splits": 0.0
        },
        {
            "Date": "2024-12-06",
            "Open": 58.400001525878906,
            "High": 58.75,
            "Low": 56.439998626708984,
            "Close": 56.7599983215332,
            "Volume": 4968300,
            "Dividends": 0.0,
            "Stock Splits": 0.0
        },
        {
            "Date": "2024-12-09",
            "Open": 57.0,
            "High": 59.22999954223633,
            "Low": 56.75,
            "Close": 58.4900016784668,
            "Volume": 5384200,
            "Dividends": 0.0,
            "Stock Splits": 0.0
        },
        {
            "Date": "2024-12-10",
            "Open": 56.7599983215332,
            "High": 57.060001373291016,
            "Low": 55.029998779296875,
            "Close": 56.709999084472656,
            "Volume": 5481200,
            "Dividends": 0.0,
            "Stock Splits": 0.0
        },
        {
            "Date": "2024-12-11",
            "Open": 56.470001220703125,
            "High": 57.189998626708984,
            "Low": 55.06999969482422,
            "Close": 56.900001525878906,
            "Volume": 6310200,
            "Dividends": 0.0,
            "Stock Splits": 0.0
        },
        {
            "Date": "2024-12-12",
            "Open": 58.5,
            "High": 59.36000061035156,
            "Low": 57.43000030517578,
            "Close": 58.0,
            "Volume": 6357500,
            "Dividends": 0.0,
            "Stock Splits": 0.0
        },
        {
            "Date": "2024-12-13",
            "Open": 59.0,
            "High": 60.34000015258789,
            "Low": 58.2400016784668,
            "Close": 59.41999816894531,
            "Volume": 7063900,
            "Dividends": 0.0,
            "Stock Splits": 0.0
        },
        {
            "Date": "2024-12-16",
            "Open": 59.02000045776367,
            "High": 59.75,
            "Low": 58.81999969482422,
            "Close": 59.16999816894531,
            "Volume": 5987000,
            "Dividends": 0.0,
            "Stock Splits": 0.0
        },
        {
            "Date": "2024-12-17",
            "Open": 58.83000183105469,
            "High": 59.79999923706055,
            "Low": 57.349998474121094,
            "Close": 57.810001373291016,
            "Volume": 7273800,
            "Dividends": 0.0,
            "Stock Splits": 0.0
        },
        {
            "Date": "2024-12-18",
            "Open": 58.369998931884766,
            "High": 60.0,
            "Low": 58.310001373291016,
            "Close": 59.4900016784668,
            "Volume": 5847100,
            "Dividends": 0.0,
            "Stock Splits": 0.0
        },
        {
            "Date": "2024-12-19",
            "Open": 59.13999938964844,
            "High": 60.16999816894531,
            "Low": 58.27000045776367,
            "Close": 59.709999084472656,
            "Volume": 16575300,
            "Dividends": 0.0,
            "Stock Splits": 0.0
        },
        {
            "Date": "2024-12-20",
            "Open": 60.0,
            "High": 60.70000076293945,
            "Low": 59.0,
            "Close": 59.58000183105469,
            "Volume": 26122300,
            "Dividends": 0.0,
            "Stock Splits": 0.0
        },
        {
            "Date": "2024-12-23",
            "Open": 59.400001525878906,
            "High": 60.5,
            "Low": 58.880001068115234,
            "Close": 60.25,
            "Volume": 4147200,
            "Dividends": 0.0,
            "Stock Splits": 0.0
        },
        {
            "Date": "2024-12-24",
            "Open": 60.20000076293945,
            "High": 60.83000183105469,
            "Low": 59.75,
            "Close": 60.83000183105469,
            "Volume": 1135000,
            "Dividends": 0.0,
            "Stock Splits": 0.0
        },
        {
            "Date": "2024-12-26",
            "Open": 60.349998474121094,
            "High": 61.130001068115234,
            "Low": 60.16999816894531,
            "Close": 60.90999984741211,
            "Volume": 3114800,
            "Dividends": 0.0,
            "Stock Splits": 0.0
        },
        {
            "Date": "2024-12-27",
            "Open": 60.77000045776367,
            "High": 61.27000045776367,
            "Low": 60.31999969482422,
            "Close": 60.599998474121094,
            "Volume": 3302700,
            "Dividends": 0.0,
            "Stock Splits": 0.0
        },
        {
            "Date": "2024-12-30",
            "Open": 60.349998474121094,
            "High": 60.65999984741211,
            "Low": 59.75,
            "Close": 60.36000061035156,
            "Volume": 2589900,
            "Dividends": 0.0,
            "Stock Splits": 0.0
        },
        {
            "Date": "2024-12-31",
            "Open": 60.650001525878906,
            "High": 61.34000015258789,
            "Low": 60.25,
            "Close": 60.58000183105469,
            "Volume": 2989900,
            "Dividends": 0.0,
            "Stock Splits": 0.0
        },
        {
            "Date": "2025-01-02",
            "Open": 61.11000061035156,
            "High": 61.779998779296875,
            "Low": 60.380001068115234,
            "Close": 60.5099983215332,
            "Volume": 3821700,
            "Dividends": 0.0,
            "Stock Splits": 0.0
        },
        {
            "Date": "2025-01-03",
            "Open": 60.68000030517578,
            "High": 62.04999923706055,
            "Low": 60.33000183105469,
            "Close": 61.47999954223633,
            "Volume": 4999600,
            "Dividends": 0.0,
            "Stock Splits": 0.0
        },
        {
            "Date": "2025-01-06",
            "Open": 61.7599983215332,
            "High": 63.7599983215332,
            "Low": 61.630001068115234,
            "Close": 62.689998626708984,
            "Volume": 4930200,
            "Dividends": 0.0,
            "Stock Splits": 0.0
        },
        {
            "Date": "2025-01-07",
            "Open": 62.880001068115234,
            "High": 63.18000030517578,
            "Low": 62.09000015258789,
            "Close": 62.61000061035156,
            "Volume": 4208100,
            "Dividends": 0.0,
            "Stock Splits": 0.0
        },
        {
            "Date": "2025-01-08",
            "Open": 62.25,
            "High": 63.61000061035156,
            "Low": 61.709999084472656,
            "Close": 63.16999816894531,
            "Volume": 5515400,
            "Dividends": 0.0,
            "Stock Splits": 0.0
        },
        {
            "Date": "2025-01-10",
            "Open": 62.88999938964844,
            "High": 63.95000076293945,
            "Low": 62.65999984741211,
            "Close": 63.42499923706055,
            "Volume": 797400,
            "Dividends": 0.0,
            "Stock Splits": 0.0
        }
    ]
}